phishing_web_collector/__init__.py
phishing_web_collector/feed_manager.py
phishing_web_collector/models.py
phishing_web_collector/taxonomies.py
phishing_web_collector/utils.py
phishing_web_collector/version.py
phishing_web_collector/feeds/__init__.py
phishing_web_collector/feeds/csv_feed.py
phishing_web_collector/feeds/feed.py
phishing_web_collector/feeds/file_based_feed.py
phishing_web_collector/feeds/json_feed.py
phishing_web_collector/feeds/url_list_feed.py
phishing_web_collector/feeds/sources/__init__.py
phishing_web_collector/feeds/sources/ad_guard_home_feed.py
phishing_web_collector/feeds/sources/binary_defence_ip_feed.py
phishing_web_collector/feeds/sources/blocklist_de_ip_feed.py
phishing_web_collector/feeds/sources/botvrij_feed.py
phishing_web_collector/feeds/sources/c2_intel_feed.py
phishing_web_collector/feeds/sources/c2_tracker_ip_feed.py
phishing_web_collector/feeds/sources/cert_pl_feed.py
phishing_web_collector/feeds/sources/dangerous_domains_feed.py
phishing_web_collector/feeds/sources/greensnow_ip_feed.py
phishing_web_collector/feeds/sources/malware_world_feed.py
phishing_web_collector/feeds/sources/mirai_security_ip_feed.py
phishing_web_collector/feeds/sources/open_phish_feed.py
phishing_web_collector/feeds/sources/phish_stats_api_feed.py
phishing_web_collector/feeds/sources/phish_stats_feed.py
phishing_web_collector/feeds/sources/phish_tank_feed.py
phishing_web_collector/feeds/sources/phishing_army_feed.py
phishing_web_collector/feeds/sources/phishing_database_feed.py
phishing_web_collector/feeds/sources/proofpoint_ips_feed.py
phishing_web_collector/feeds/sources/threat_view_feed.py
phishing_web_collector/feeds/sources/tweet_feed_feed.py
phishing_web_collector/feeds/sources/url_abuse_feed.py
phishing_web_collector/feeds/sources/url_house_feed.py
phishing_web_collector/feeds/sources/valdin_feed.py
phishing_web_collector-0.2.1.dist-info/licenses/LICENSE
phishing_web_collector-0.2.1.dist-info/METADATA
phishing_web_collector-0.2.1.dist-info/WHEEL
phishing_web_collector-0.2.1.dist-info/top_level.txt
phishing_web_collector-0.2.1.dist-info/RECORD
