Metadata-Version: 2.4
Name: phishing-web-collector
Version: 0.2.1
Summary: Phishing Web Collector
Home-page: https://github.com/damianfraszczak/phishing-web-collector
Author: Damian Frąszczak, Edyta Frąszczak
Author-email: damian.fraszczak@wat.edu.pl
License: MIT
Keywords: phishing_websites malicious_websites phishing
Classifier: Development Status :: 4 - Beta
Classifier: Intended Audience :: Developers
Classifier: Topic :: Software Development :: Build Tools
Classifier: License :: OSI Approved :: MIT License
Classifier: Programming Language :: Python
Classifier: Programming Language :: Python :: 3
License-File: LICENSE
Requires-Dist: aiohttp
Requires-Dist: requests
Provides-Extra: lint
Requires-Dist: bandit; extra == "lint"
Requires-Dist: black; extra == "lint"
Requires-Dist: flake8; extra == "lint"
Requires-Dist: flake8-debugger; extra == "lint"
Requires-Dist: flake8-docstrings; extra == "lint"
Requires-Dist: flake8-isort; extra == "lint"
Requires-Dist: mypy; extra == "lint"
Requires-Dist: pylint; extra == "lint"
Dynamic: author
Dynamic: author-email
Dynamic: classifier
Dynamic: description
Dynamic: description-content-type
Dynamic: home-page
Dynamic: keywords
Dynamic: license
Dynamic: license-file
Dynamic: provides-extra
Dynamic: requires-dist
Dynamic: summary
